llm_fs_tools/__init__.py
llm_fs_tools/compat.py
llm_fs_tools/exceptions.py
llm_fs_tools/core/__init__.py
llm_fs_tools/core/executor.py
llm_fs_tools/core/file_handle.py
llm_fs_tools/core/schemas.py
llm_fs_tools/core/security.py
llm_fs_tools/core/tools.py
llm_fs_tools/core/write_tools.py
llm_fs_tools/platform/__init__.py
llm_fs_tools/platform/paths.py
llm_fs_tools/platform/secure_open.py
llm_fs_tools/utils/__init__.py
llm_fs_tools/utils/audit.py
llm_fs_tools/utils/streaming.py
llm_fs_tools-1.1.1.dist-info/licenses/LICENSE
llm_fs_tools-1.1.1.dist-info/METADATA
llm_fs_tools-1.1.1.dist-info/WHEEL
llm_fs_tools-1.1.1.dist-info/top_level.txt
llm_fs_tools-1.1.1.dist-info/RECORD
