Metadata-Version: 2.4
Name: llm-fs-tools
Version: 1.1.1
Summary: Production-ready filesystem access tools for LLMs with TOCTOU protection
Author: Daniel T Sasser II
License-Expression: MIT
Project-URL: Homepage, https://github.com/dansasser/llm-filesystem-tools
Project-URL: Documentation, https://github.com/dansasser/llm-filesystem-tools#readme
Project-URL: Repository, https://github.com/dansasser/llm-filesystem-tools.git
Project-URL: Issues, https://github.com/dansasser/llm-filesystem-tools/issues
Keywords: llm,filesystem,tools,security,ai,function-calling
Classifier: Development Status :: 4 - Beta
Classifier: Intended Audience :: Developers
Classifier: Programming Language :: Python :: 3
Classifier: Programming Language :: Python :: 3.10
Classifier: Programming Language :: Python :: 3.11
Classifier: Programming Language :: Python :: 3.12
Classifier: Topic :: Software Development :: Libraries :: Python Modules
Classifier: Topic :: System :: Filesystems
Classifier: Topic :: Scientific/Engineering :: Artificial Intelligence
Requires-Python: >=3.10
License-File: LICENSE
Provides-Extra: dev
Requires-Dist: pytest>=7.0; extra == "dev"
Requires-Dist: pytest-cov>=4.0; extra == "dev"
Requires-Dist: black>=22.0; extra == "dev"
Requires-Dist: mypy>=1.0; extra == "dev"
Requires-Dist: ruff>=0.1.0; extra == "dev"
Dynamic: license-file
